gensbo/__init__.py
gensbo/gensbo.py
gensbo/core/__init__.py
gensbo/core/problem.py
gensbo/core/variable.py
gensbo/optimizers/__init__.py
gensbo/optimizers/optimizer.py
gensbo/optimizers/pso/__init__.py
gensbo/optimizers/pso/mopso.py
gensbo/optimizers/pso/pso.py
gensbo/optimizers/pso/sopso.py
gensbo/simulators/__init__.py
gensbo/simulators/simulator.py
gensbo/simulators/energyplus/__init__.py
gensbo/simulators/trnsys/__init__.py
gensbo/simulators/trnsys/trnsys.py
gensbo/simulators/userfunction/__init__.py
gensbo/simulators/userfunction/userfunction.py
gensbo/tools/__init__.py
gensbo/tools/dp.py
gensbo/tools/util.py
gensbo-0.1.0.dist-info/LICENSE
gensbo-0.1.0.dist-info/METADATA
gensbo-0.1.0.dist-info/WHEEL
gensbo-0.1.0.dist-info/top_level.txt
gensbo-0.1.0.dist-info/RECORD
