Metadata-Version: 2.1
Name: gensbo
Version: 0.1.0
Summary: gensbo—a General Simulation Based Optimizer
Home-page: https://github.com/ai4energy/gensbo.git
Author: Mingtao Li
Author-email: mingtao.li@gmail.com
License: UNKNOWN
Keywords: optimization,simulation,pso,tool
Platform: UNKNOWN
Classifier: Programming Language :: Python :: 3
Classifier: License :: OSI Approved :: MIT License
Classifier: Operating System :: OS Independent
